{
    "id": "7d35bdbe-d3c2-40d9-b2ea-4823c1cf2181",
    "status": "Approved",
    "is_completed": true,
    "timestamp": 1782451848351.0132,
    "ai_comment": "안녕하세요, 홍길동테스트 학생의 성장에 대한 깊은 관심과 기대를 품고 계신 학부모님.\n\n저희 '피지컬업 333 피지컬 코칭 팀'은 홍길동테스트 학생의 현재 성장 데이터를 면밀히 분석하고, 잠재력을 최대한 발휘할 수 있는 초프리미엄 맞춤형 성장 로드맵을 제시해 드리고자 합니다. 저희 팀은 학부모님께서 깊이 신뢰하고 즉각 실천하실 수 있도록 가장 전문적이고 섬세한 가이드를 제공할 것을 약속드립니다.\n\n---\n\n**[피지컬업 333 피지컬 성장 분석]**\n\n홍길동테스트 학생의 BioCode는 2-3-2로 분석되었습니다. 이는 선천적인 성장 잠재력(2등급)은 평균 수준이며, 생활 습관(2등급) 또한 평균 범주에 속하지만, 가장 중요한 대사 효율성(3등급)이 현저히 부족한 상태임을 명확히 보여주고 있습니다. 대사 효율성 3등급은 영양소를 에너지로 전환하고 성장 인자를 활성화하는 신체 내부 시스템이 원활하게 작동하지 못하고 있다는 강력한 신호입니다.\n\n현재 홍길동테스트 학생의 유전 예상 신장 대비 실측 신장 격차가 -7.1cm라는 것은 매우 중요한 지표입니다. 이는 홍길동테스트 학생이 가진 본래의 성장 잠재력을 현재 충분히 발휘하지 못하고 있으며, 신체 대사 기능의 저하와 직접적으로 연관된 것으로 분석됩니다. 즉, 충분한 영양분이 공급되어도 대사 시스템이 이를 효과적으로 활용하지 못하고, 성장호르몬의 분비 및 작용 또한 원활하지 않을 가능성이 높습니다.\n\n여기에 성장의 주된 저해(제한) 원인이 ‘수면 및 활동량 부족’으로 지목된 것은, 대사 효율성 3등급과 직접적인 연결고리를 가집니다. 부족한 수면은 성장호르몬 분비를 저해하고 신체 회복을 늦추며, 활동량 부족은 신체 대사율을 떨어뜨리고 뼈에 필요한 적절한 성장 자극을 주지 못합니다. 이 두 가지 요인이 복합적으로 작용하여 유전적인 성장 잠재력(2등급)을 억누르고 현재의 신장 격차를 발생시키는 핵심 원인으로 작용하고 있음을 저희 '피지컬업 333'은 확인하였습니다.\n\n저희 팀은 홍길동테스트 학생이 가진 평균 이상의 성장 잠재력을 최대한 발현시키기 위해 대사 효율성 개선, 그리고 수면 및 활동량 증진에 초점을 맞춘 초프리미엄 맞춤형 솔루션이 시급하다고 판단하고 있습니다.\n\n---\n\n**[피지컬업 333 영양 및 소화 흡수 전략]**\n\n홍길동테스트 학생의 '표준 신체 대사형' 체질은 일반적으로 균형 잡힌 영양 섭취에 잘 반응하는 특징을 가집니다. 그러나 현재 '대사 효율성 3등급'과 '활동량 부족'으로 인해 단순히 잘 먹는 것만으로는 충분한 성장을 기대하기 어렵습니다. 섭취된 영양소가 체내에서 얼마나 효율적으로 소화, 흡수되고 활용되는지가 핵심입니다. 이에 저희 '피지컬업 333'은 다음의 영양 및 소화 흡수 전략을 제안합니다.\n\n1.  **흡수율 극대화를 위한 식단 구성:**\n    *   **단백질:** 성장과 근육 발달의 기본입니다. 닭가슴살, 살코기, 생선, 두부, 콩류, 계란 등 양질의 단백질을 매끼 충분히 섭취해야 합니다. 특히 운동 후에는 단백질 섭취가 더욱 중요합니다.\n    *   **탄수화물:** 활동 에너지의 주원료입니다. 통곡물(현미밥, 오트밀), 고구마, 감자 등 정제되지 않은 복합 탄수화물을 통해 지속적인 에너지 공급과 혈당 안정성을 유지해야 합니다. 설탕이 많은 단 음식은 피해야 합니다.\n    *   **건강한 지방:** 호르몬 생성과 영양소 흡수에 필수적입니다. 견과류, 아보카도, 등푸른생선(오메가-3), 올리브 오일 등을 적정량 섭취하여 균형을 맞춥니다.\n    *   **성장 필수 미네랄 및 비타민:** 칼슘, 비타민 D, 아연, 마그네슘, 비타민 K는 뼈 성장과 성장호르몬 활성화에 직접적으로 관여합니다. 우유, 치즈, 뼈째 먹는 생선, 녹색 잎채소, 버섯, 해조류, 굴 등을 통해 풍부하게 섭취해야 합니다.\n\n2.  **소화 및 흡수 효율 증진:**\n    *   **천천히, 꼭꼭 씹어 먹기:** 음식을 충분히 씹는 과정은 소화 효소 분비를 촉진하고 영양소 흡수율을 높입니다. 식사 시간에 여유를 가지고 즐겁게 식사하는 습관을 들여야 합니다.\n    *   **신선한 채소와 과일:** 비타민, 미네랄은 물론, 소화를 돕는 효소와 섬유질이 풍부합니다. 매끼니 다양한 색깔의 채소를 충분히 섭취하고, 간식으로는 과일을 권장합니다.\n    *   **발효 식품:** 김치, 요거트, 된장 등은 장 건강에 유익한 유익균을 공급하여 영양소 흡수를 돕고 면역력을 강화합니다. 장 건강은 대사 효율성과 직결됩니다.\n    *   **충분한 수분 섭취:** 물은 영양소 운반, 체온 조절, 노폐물 배출 등 모든 신체 대사 활동의 기본입니다. 하루 1.5~2리터 이상의 물을 꾸준히 마시는 습관이 중요합니다.\n\n3.  **영양 보충 가이드 (선택 사항):**\n    *   '대사 효율성 3등급'을 고려할 때, 식단만으로 부족할 수 있는 특정 미량 영양소의 보충을 고려할 수 있습니다. 특히 성장기 필수 요소인 비타민 D, 칼슘, 마그네슘, 아연 등은 신체 활동량과 일조량, 식단에 따라 부족해지기 쉽습니다. 이러한 보충제는 흡수율이 높은 형태로, 전문가의 가이드를 받아 현명하게 선택하는 것이 중요합니다. 인공 감미료나 첨가물이 적은 제품을 우선적으로 고려하시기 바랍니다.\n\n---\n\n**[피지컬업 333 맞춤형 운동 및 수면 설계]**\n\n성장의 주된 저해 원인인 '수면 및 활동량 부족'을 해소하고, 야구 종목에 특화된 피지컬 성장을 도모하기 위해 저희 '피지컬업 333'은 홍길동테스트 학생을 위한 맞춤형 운동 및 수면 설계를 제안합니다.\n\n**1. 피지컬업 333 맞춤형 운동 설계 (야구 종목 특성 반영):**\n홍길동테스트 학생의 희망 운동 종목인 야구는 단순한 훈련을 넘어 전신 근육의 협응력, 순발력, 민첩성, 유연성을 요구하며, 이는 뼈 성장에 매우 긍정적인 자극을 제공합니다.\n\n*   **뼈 성장 자극 운동 요법:**\n    *   **체중 부하 운동:** 뼈에 적절한 스트레스를 주어 성장판을 자극하고 뼈 밀도를 높이는 데 필수적입니다.\n        *   **점프 훈련:** 제자리 점프, 박스 점프, 한 발 점프 등을 통해 성장판에 수직 방향의 자극을 줍니다. 야구의 도루, 캐치 시 점프 동작 등과 연관하여 훈련합니다.\n        *   **달리기 및 스프린트:** 야구의 베이스러닝, 수비 시 빠른 대시 동작은 전신 뼈 성장을 촉진합니다. 다양한 속도와 방향으로 달리는 훈련을 포함합니다.\n        *   **줄넘기:** 전신 근육을 사용하며, 착지 시 뼈에 규칙적인 자극을 줍니다. 매일 10~15분 정도를 목표로 꾸준히 실천합니다.\n    *   **유연성 및 코어 강화 운동:**\n        *   **스트레칭:** 야구 동작의 부드러움과 넓은 가동 범위를 위해 어깨, 허리, 골반, 다리 등 전신 스트레칭을 매일 충분히 실시합니다. 성장판 주변 조직의 유연성을 높여 뼈가 효율적으로 성장할 수 있는 환경을 조성합니다.\n        *   **코어 근력 운동:** 플랭크, 브릿지, 버드독 등 맨몸 코어 운동은 신체 균형감각과 안정성을 높여 야구 실력 향상은 물론, 성장판에 무리 없는 올바른 자세를 유지하는 데 도움을 줍니다. 이는 성장호르몬 분비 촉진에도 기여합니다.\n    *   **야구 훈련 외 추가 활동:** 주 3~4회, 최소 60분 이상의 중강도 활동을 권장합니다. 농구, 배드민턴, 가벼운 등산, 자전거 타기 등 다양한 활동을 통해 전신을 골고루 사용하고 활동량 부족을 해소합니다. 이는 스트레스 해소와 신진대사 활성화에도 도움을 줍니다.\n    *   **놀이 중심의 활동:** 운동을 숙제가 아닌 즐거움으로 인식할 수 있도록 친구들과 함께하는 놀이나 스포츠 활동을 적극 권장합니다. 지속 가능한 성장을 위해서는 재미가 가장 중요합니다.\n\n**2. 피지컬업 333 핵심 수면 타이밍 및 수면 환경 설계:**\n수면은 성장호르몬 분비의 황금 시간이며, '수면 부족'은 성장을 저해하는 가장 큰 요소 중 하나입니다. 홍길동테스트 학생에게는 질 높은 수면 환경 조성이 절실합니다.\n\n*   **핵심 성장호르몬 분비 촉진 타이밍:**\n    *   성장호르몬은 주로 밤 10시부터 새벽 2시 사이에 가장 깊은 수면 단계(Non-REM 수면 3-4단계)에서 활발하게 분비됩니다. 이 황금 시간대에 깊은 잠에 들 수 있도록, 홍길동테스트 학생은 **밤 9시~9시 30분에는 반드시 잠자리에 들 준비를 마치고, 늦어도 밤 10시 이전에 취침**할 것을 목표로 삼아야 합니다.\n    *   총 수면 시간은 유소년기에 필요한 9~10시간을 반드시 확보해야 합니다. 이는 단순히 잠을 자는 시간을 넘어, 신체 회복과 면역력 강화, 다음날 활동을 위한 에너지 충전의 시간입니다.\n\n*   **최적의 수면 환경 조성:**\n    *   **규칙적인 수면 패턴:** 주말에도 평일과 비슷한 시간에 잠들고 일어나는 습관을 유지하여 신체 리듬을 안정화시킵니다.\n    *   **수면 전 전자기기 사용 제한:** 스마트폰, 태블릿, TV 등의 블루라이트는 멜라토닌(수면 유도 호르몬) 분비를 억제하여 수면의 질을 저하시킵니다. 취침 1시간 전부터는 모든 전자기기 사용을 중단하고 독서나 가벼운 대화 등 정적인 활동을 권장합니다.\n    *   **어둡고 조용하며 시원한 침실:** 최적의 수면 온도는 18~22도이며, 빛과 소음을 최대한 차단하여 깊은 잠을 유도합니다.\n    *   **자기 전 과도한 활동/음식 섭취 자제:** 취침 직전의 격렬한 운동이나 과식은 숙면을 방해할 수 있습니다. 가벼운 스트레칭이나 미지근한 물 샤워는 도움이 될 수 있습니다.\n    *   **카페인 섭취 금지:** 커피, 에너지 드링크, 일부 탄산음료에 포함된 카페인은 수면 방해의 주범이므로 절대 피해야 합니다.\n\n---\n\n사랑하는 홍길동테스트 학생의 학부모님,\n\n저희 '피지컬업 333 피지컬 코칭 팀'은 홍길동테스트 학생이 가진 성장 잠재력을 믿으며, 위에 제시된 초프리미엄 맞춤형 가이드가 학생의 성장에 매우 중요한 전환점이 될 것이라고 확신합니다. 꾸준하고 일관된 노력은 반드시 빛을 발할 것입니다. 저희 팀은 학부모님과 홍길동테스트 학생의 빛나는 미래를 항상 응원하며, 지속적인 성장을 위해 함께 걸어 나갈 준비가 되어 있습니다. 궁금한 점이 있으시면 언제든 저희 팀에 문의해 주십시오.\n\n감사합니다.\n\n피지컬업 333 피지컬 코칭 팀 드림",
    "name": "홍길동테스트",
    "gender": "남",
    "birth_date": "2013-05-15",
    "grade": "초등 6학년",
    "sports": "야구",
    "position": "투수",
    "phone": "010-1234-5678",
    "father_height": 178.5,
    "mother_height": 162.0,
    "current_height": 155.5,
    "current_weight": 48.5,
    "body_fat": null,
    "skeletal_muscle": null,
    "wingspan": 157.0,
    "survey_responses": [
        3,
        3,
        3,
        3,
        3,
        3,
        3,
        3,
        3,
        3,
        3,
        3,
        3,
        3,
        3,
        3,
        3,
        3,
        3,
        3,
        3,
        3,
        3,
        3
    ],
    "is_free": true,
    "reservation_date": "2026-06-26",
    "scheduled_at": 1782435600000.0,
    "inspected_by": "representative"
}